orcid2markdown/__init__.py
orcid2markdown-0.0.1a0.dist-info/LICENSE
orcid2markdown-0.0.1a0.dist-info/METADATA
orcid2markdown-0.0.1a0.dist-info/WHEEL
orcid2markdown-0.0.1a0.dist-info/top_level.txt
orcid2markdown-0.0.1a0.dist-info/RECORD
