Metadata-Version: 2.1
Name: orcid2markdown
Version: 0.0.1a0
Summary: A simple package to parse an ORCID works entry into a Markdown format for static website generators
Home-page: https://github.com/pedrobcst/orcid2markdown
Author: Pedro B. C.
Author-email: pedro@pedrobcst.com
License: UNKNOWN
Project-URL: Bug Tracker, https://github.com/pedrobcst/orcid2markdown/issues
Platform: UNKNOWN
Classifier: Programming Language :: Python :: 3
Classifier: License :: OSI Approved :: MIT License
Classifier: Operating System :: OS Independent
Requires-Python: >=3.7
License-File: LICENSE
Requires-Dist: habanero
Requires-Dist: bibtexparser
